{"url": "https://www.securityweek.com/stryker-says-malicious-file-found-during-probe-into-iran-linked-attack/", "original_lang": "en", "summary_vi": "Stryker phát hiện tập tin độc hại trong quá trình điều tra vụ tấn công mạng liên quan đến Iran\n\nTập đoàn công nghệ y tế khổng lồ Stryker đã chia sẻ thông tin cập nhật liên quan đến cuộc điều tra về vụ tấn công mạng có liên hệ với Iran gần đây, tiết lộ rằng một tập tin độc hại được những kẻ tấn công sử dụng đã được xác định.\n\nSự cố của Stryker được đưa ra ánh sáng vào ngày 11 tháng 3, với việc nhóm hacker Handala nhận trách nhiệm về vụ tấn công.\n\nHandala, được tin rộng rãi là một danh tính tin tặc hoạt động vì mục đích chính trị do Bộ Tình báo và An ninh Iran hay MOIS kiểm soát, tuyên bố đã xóa dữ liệu của hơn 200.000 thiết bị, buộc Stryker phải đóng cửa các văn phòng tại hàng chục quốc gia.\n\nMột số báo cáo ban đầu chỉ ra rằng Handala đã sử dụng mã độc xóa dữ liệu trong vụ tấn công, nhóm này vốn nổi tiếng với việc sử dụng loại mã độc như vậy, nhưng Stryker cho biết họ không tìm thấy bằng chứng nào về việc mã độc hoặc mã độc tống tiền được triển khai trên hệ thống của mình.\n\nKịch bản có khả năng nhất dựa trên các bằng chứng có sẵn cho đến nay là các tin tặc đã xóa hệ thống bằng cách lạm dụng phiên bản Microsoft Intune của Stryker, vốn được sử dụng để quản lý từ xa các thiết bị đầu cuối máy tính để bàn và di động cũng như các ứng dụng trong tổ chức. Có một số dấu hiệu cho thấy Handala đã tận dụng thông tin xác thực thu được thông qua mã độc đánh cắp thông tin để giành quyền truy cập.\n\nStryker cho biết sự cố đã làm gián đoạn quá trình xử lý đơn hàng, sản xuất và vận chuyển. Trong một tuyên bố phát đi hôm thứ Hai, công ty cho biết họ đã đạt được tiến bộ có ý nghĩa trong việc khôi phục các hệ thống bị ảnh hưởng.\n\nLần đầu tiên, công ty cũng đã chia sẻ một số thông tin kỹ thuật từ cuộc điều tra về sự cố này.\n\nĐầu cuộc điều tra, chúng tôi tin rằng không có dấu hiệu của mã độc tống tiền hay phần mềm độc hại, Stryker cho biết. Đi sâu hơn vào quá trình điều tra, cùng với Palo Alto Networks Unit 42 và các chuyên gia khác, chúng tôi xác định rằng tác nhân đe dọa đã sử dụng một tập tin độc hại để chạy các lệnh cho phép chúng che giấu hoạt động của mình khi ở trong hệ thống của chúng tôi.\n\nCông ty nói thêm, Để làm rõ, tập tin này không có khả năng lây lan, dù là bên trong hay bên ngoài môi trường của chúng tôi. Quan trọng nhất, chưa có thời điểm nào cuộc điều tra của chúng tôi xác định được hoạt động độc hại nhắm vào khách hàng, nhà cung cấp, bên bán hàng hoặc đối tác của chúng tôi.\n\nDựa trên mô tả ngắn gọn này, tập tin độc hại được Stryker đề cập có thể là một tệp nhị phân tùy chỉnh nhỏ hoặc một tập lệnh thay vì là phần mềm độc hại thực sự. Tuy nhiên, điều này cho thấy các tin tặc đã triển khai các công cụ riêng của chúng trên các hệ thống bị xâm nhập và không chỉ dựa vào phần mềm hiện có để thực hiện các hoạt động của mình.\n\nNgoài việc chia sẻ thông tin cập nhật về cuộc điều tra và nỗ lực khôi phục, Stryker đã công bố một đánh giá từ Palo Alto Networks để cho thấy rằng sự cố đã được ngăn chặn.\n\nChính phủ Mỹ đã chính thức liên kết Handala với MOIS của Iran và đã đánh sập một số trang web do tác nhân đe dọa này sử dụng.\n\nNgoài ra, FBI đã đưa ra một cảnh báo chia sẻ thông tin về các cuộc tấn công được cho là do các tác nhân đe dọa thuộc MOIS như Handala thực hiện, bao gồm cả loại mã độc mà chúng sử dụng.\n\nFBI đã thu thập được các mẫu mã độc thông qua các cuộc điều tra. Các mẫu này được phân loại là mã độc ngụy trang giai đoạn 1, mã độc cấy ghép dai dẳng giai đoạn 2 và mã độc giai đoạn 2 liên quan có chứa các chức năng bổ sung hoặc độc đáo. Giai đoạn 1 thường ngụy trang dưới dạng các ứng dụng thường dùng như Pictory, KeePass và Telegram và chứa các tệp nhị phân cho giai đoạn tiếp theo của mã độc.\n\nMã độc cấy ghép dai dẳng sinh ra sau khi thực thi mã độc ngụy trang và có thể có sự tương tác của người dùng với ứng dụng độc hại. Ở giai đoạn này, các tác nhân mạng thuộc MOIS của Iran đã cấu hình một hệ thống chỉ huy và kiểm soát C2 sử dụng bot Telegram, cho phép giao tiếp hai chiều giữa thiết bị bị xâm nhập và api.telegram.org. FBI coi mã độc ngụy trang và mã độc cấy ghép dai dẳng là chức năng cốt lõi cho chiến dịch mã độc này.\n\nStryker xác nhận rằng họ đang làm việc với các cơ quan chính phủ Mỹ trong cuộc điều tra về sự cố, nhưng loại mã độc được mô tả trong cảnh báo của FBI khó có khả năng liên quan đến cuộc tấn công vào công ty công nghệ y tế này nếu thực sự không có phần mềm độc hại nào liên quan.\n\nTin liên quan: Oracle phát hành bản vá khẩn cấp cho lỗ hổng Identity Manager nghiêm trọng", "audio_url": "/api/news/audio/4a05e7881c3eff0de2c3caf36394ce04.mp3", "hash": "4a05e7881c3eff0de2c3caf36394ce04"}